alteryx_open_src_update_checker/__init__.py
alteryx_open_src_update_checker/functions.py
alteryx_open_src_update_checker/settings.py
alteryx_open_src_update_checker/utils.py
alteryx_open_src_update_checker/version.py
alteryx_open_src_update_checker/tests/__init__.py
alteryx_open_src_update_checker/tests/test_ayx_open_source_update_checker.py
alteryx_open_src_update_checker/tests/test_version.py
alteryx_open_src_update_checker-3.1.0.dist-info/LICENSE
alteryx_open_src_update_checker-3.1.0.dist-info/METADATA
alteryx_open_src_update_checker-3.1.0.dist-info/WHEEL
alteryx_open_src_update_checker-3.1.0.dist-info/top_level.txt
alteryx_open_src_update_checker-3.1.0.dist-info/RECORD
