Metadata-Version: 2.1
Name: alteryx-open-src-update-checker
Version: 3.1.0
Summary: an update checker for alteryx open source libraries
Author-email: "Alteryx, Inc." <open_source_support@alteryx.com>
Maintainer-email: "Alteryx, Inc." <open_source_support@alteryx.com>
License: BSD 3-clause
Project-URL: Source Code, https://github.com/alteryx/alteryx-open-src-update-checker/
Project-URL: Issue Tracker, https://github.com/alteryx/alteryx-open-src-update-checker/issues
Project-URL: Twitter, https://twitter.com/alteryxoss
Project-URL: Chat, https://join.slack.com/t/alteryx-oss/shared_invite/zt-182tyvuxv-NzIn6eiCEf8TBziuKp0bNA
Keywords: data science,machine learning
Classifier: Development Status :: 5 - Production/Stable
Classifier: Intended Audience :: Science/Research
Classifier: Intended Audience :: Developers
Classifier: Topic :: Software Development
Classifier: Topic :: Scientific/Engineering
Classifier: Programming Language :: Python
Classifier: Programming Language :: Python :: 3
Classifier: Programming Language :: Python :: 3.8
Classifier: Programming Language :: Python :: 3.9
Classifier: Programming Language :: Python :: 3.10
Classifier: Programming Language :: Python :: 3.11
Classifier: Operating System :: Microsoft :: Windows
Classifier: Operating System :: POSIX
Classifier: Operating System :: Unix
Classifier: Operating System :: MacOS
Requires-Python: <4,>=3.8
License-File: LICENSE
Requires-Dist: requests (>=2.22.0)
Provides-Extra: dev
Requires-Dist: ruff (>=0.0.239) ; extra == 'dev'
Requires-Dist: black[jupyter] (>=23.1.0) ; extra == 'dev'
Requires-Dist: pre-commit (>=2.20.0) ; extra == 'dev'
Provides-Extra: test
Requires-Dist: pip (>=21.3.1) ; extra == 'test'
Requires-Dist: pytest (>=7.1.2) ; extra == 'test'
Requires-Dist: pytest-cov (>=3.0.0) ; extra == 'test'
Requires-Dist: pytest-xdist (>=2.5.0) ; extra == 'test'
Requires-Dist: featuretools ; extra == 'test'
Requires-Dist: composeml ; extra == 'test'
Requires-Dist: evalml ; extra == 'test'
Requires-Dist: woodwork ; extra == 'test'
Requires-Dist: mock (>=3.0.5) ; extra == 'test'
